{
  "$schema": "https://biomejs.dev/schemas/2.3.7/schema.json",
  "formatter": {
    "enabled": true,
    "formatWithErrors": false,
    "indentStyle": "space",
    "lineWidth": 100
  },
  "linter": {
    "enabled": true,
    "rules": {
      "recommended": true,
      "suspicious": {
        "noConsole": "error"
      }
    }
  },
  "assist": {
    "enabled": true,
    "actions": {
      "source": {
        "organizeImports": "on",
        "useSortedKeys": "off"
      }
    }
  },
  "vcs": {
    "enabled": true,
    "clientKind": "git",
    "useIgnoreFile": true
  },
  "files": {
    "ignoreUnknown": false
  },
  "javascript": {
    "formatter": {
      "quoteStyle": "double"
    }
  },
  "css": {
    "parser": {
      "tailwindDirectives": true
    }
  }
}
